bluer_academy/__init__.py
bluer_academy/__main__.py
bluer_academy/logger.py
bluer_academy/.abcli/abcli.sh
bluer_academy/.abcli/actions.sh
bluer_academy/.abcli/alias.sh
bluer_academy/.abcli/bluer_academy.sh
bluer_academy/.abcli/tests/README.sh
bluer_academy/.abcli/tests/help.sh
bluer_academy/.abcli/tests/version.sh
bluer_academy/academy/__init__.py
bluer_academy/academy/classes/__init__.py
bluer_academy/academy/classes/syllabus.py
bluer_academy/academy/classes/topic.py
bluer_academy/academy/syllabus/QGIS.py
bluer_academy/academy/syllabus/__init__.py
bluer_academy/academy/syllabus/aiart.py
bluer_academy/academy/syllabus/bash.py
bluer_academy/academy/syllabus/basic_electronics.py
bluer_academy/academy/syllabus/city_watching.py
bluer_academy/academy/syllabus/cloud.py
bluer_academy/academy/syllabus/consts.py
bluer_academy/academy/syllabus/documentation.py
bluer_academy/academy/syllabus/flow_management.py
bluer_academy/academy/syllabus/geospatial.py
bluer_academy/academy/syllabus/geospatial_semseg.py
bluer_academy/academy/syllabus/geospatial_sources.py
bluer_academy/academy/syllabus/geospatial_timeseries.py
bluer_academy/academy/syllabus/github.py
bluer_academy/academy/syllabus/journal.py
bluer_academy/academy/syllabus/linux.py
bluer_academy/academy/syllabus/machine_vision.py
bluer_academy/academy/syllabus/math.py
bluer_academy/academy/syllabus/objects.py
bluer_academy/academy/syllabus/plugins.py
bluer_academy/academy/syllabus/pypi.py
bluer_academy/academy/syllabus/python.py
bluer_academy/academy/syllabus/rccar.py
bluer_academy/academy/syllabus/rccar_arduino.py
bluer_academy/academy/syllabus/sandbox.py
bluer_academy/academy/syllabus/sbc.py
bluer_academy/academy/syllabus/template.py
bluer_academy/academy/syllabus/testing.py
bluer_academy/academy/syllabus/ugv.py
bluer_academy/academy/syllabus/yolo.py
bluer_academy/ai4k/__init__.py
bluer_academy/ai4k/experiments.py
bluer_academy/help/__init__.py
bluer_academy/help/__main__.py
bluer_academy/help/functions.py
bluer_academy-5.180.1.dist-info/licenses/LICENSE
bluer_academy-5.180.1.dist-info/METADATA
bluer_academy-5.180.1.dist-info/WHEEL
bluer_academy-5.180.1.dist-info/top_level.txt
bluer_academy-5.180.1.dist-info/RECORD
