Metadata-Version: 2.4
Name: bluer_academy
Version: 5.180.1
Summary: 📐 an academy for practical AI in Iran.
Home-page: https://github.com/kamangir/bluer-academy
Author: Arash Abadpour (Kamangir)
Author-email: arash.abadpour@gmail.com
License: CC0-1.0
Classifier: Programming Language :: Python :: 3
Classifier: Programming Language :: Unix Shell
Classifier: Operating System :: OS Independent
License-File: LICENSE
Requires-Dist: bluer_ai
Requires-Dist: bluer_flow
Requires-Dist: networkx
Requires-Dist: pydot==3.0.4
Dynamic: author
Dynamic: author-email
Dynamic: classifier
Dynamic: description
Dynamic: description-content-type
Dynamic: home-page
Dynamic: license
Dynamic: license-file
Dynamic: requires-dist
Dynamic: summary
